turtleshell/__init__.py
turtleshell/core.py
turtleshell-1.4.0.dist-info/METADATA
turtleshell-1.4.0.dist-info/WHEEL
turtleshell-1.4.0.dist-info/top_level.txt
turtleshell-1.4.0.dist-info/RECORD
